[
  {
    "baslik": "Mustafa Met > Pulitzer :(",
    "alt_baslik": "",
    "gorsel": "assets/saygi/mustafa_met.jpg",
    "metin": ""
  },
  {
    "baslik": "Ölümsüzdür",
    "alt_baslik": "",
    "gorsel": "assets/saygi/olumsuzdur.jpg",
    "metin": ""
  },
  {
    "baslik": "Anne gibi Anne",
    "alt_baslik": "",
    "gorsel": "assets/saygi/anne_gibi_anne.jpg",
    "metin": ""
  },
  {
    "baslik": "Kdz. Ereğli > La Masia. İtirazı olan?",
    "alt_baslik": "",
    "gorsel": "assets/saygi/kdz_eregli.jpg",
    "metin": ""
  },
  {
    "baslik": "İşte Gerçek Taraftar",
    "alt_baslik": "",
    "gorsel": "assets/saygi/taraftar.jpg",
    "metin": ""
  },
  {
    "baslik": "Komando oyuna böyle girer",
    "alt_baslik": "",
    "gorsel": "assets/saygi/komando.jpg",
    "metin": ""
  },
  {
    "baslik": "Sinyor",
    "alt_baslik": "",
    "gorsel": "assets/saygi/sinyor.jpg",
    "metin": ""
  },
  {
    "baslik": "Vur Koş #masterclass",
    "alt_baslik": "",
    "gorsel": "assets/saygi/vur_kos.jpg",
    "metin": ""
  },
  {
    "baslik": "Kaplanfito Instagramı fethetmedi mi?",
    "alt_baslik": "",
    "gorsel": "assets/saygi/kaplanfito.jpg",
    "metin": ""
  },
  {
    "baslik": "Futbol 101",
    "alt_baslik": "",
    "gorsel": "assets/saygi/futbol101.jpg",
    "metin": ""
  },
  {
    "baslik": "Bio dediğin",
    "alt_baslik": "",
    "gorsel": "assets/saygi/bio_millitakimlar.jpg",
    "metin": ""
  }
]